cruxes/__init__.py
cruxes/cli.py
cruxes/utils/body_trajectory.py
cruxes/utils/compare_trajectories.py
cruxes/utils/draw_helpers.py
cruxes/utils/file_operations.py
cruxes/utils/kamlan_filter.py
cruxes/utils/merge_videos.py
cruxes/utils/plot_pose.py
cruxes/utils/pose_helpers.py
cruxes/utils/warp_video.py
cruxes/utils/utils/images.py
cruxes-0.1.6.dist-info/licenses/LICENSE
cruxes-0.1.6.dist-info/METADATA
cruxes-0.1.6.dist-info/WHEEL
cruxes-0.1.6.dist-info/entry_points.txt
cruxes-0.1.6.dist-info/top_level.txt
cruxes-0.1.6.dist-info/RECORD
