Metadata-Version: 2.4
Name: cruxes
Version: 0.1.6
Summary: A set of computer vision tools for analyzing your climbing videos.
Author-email: Tommy Liu <i@tjtl.io>
License: MIT License
Project-URL: Homepage, https://github.com/tommyjtl/climbing-analysis-toolbox
Classifier: Programming Language :: Python :: 3
Classifier: License :: OSI Approved :: MIT License
Classifier: Operating System :: OS Independent
Requires-Python: >=3.11
License-File: LICENSE
Requires-Dist: termcolor>=3.1.0
Requires-Dist: opencv-python>=4.11.0.86
Requires-Dist: numpy>=1.26.4
Requires-Dist: mediapipe>=0.10.20
Requires-Dist: scipy>=1.11.0
Dynamic: license-file
